iotlabwscli/__init__.py
iotlabwscli/parser.py
iotlabwscli/websocket.py
iotlabwscli/tests/__init__.py
iotlabwscli/tests/iotlabwscli_mock.py
iotlabwscli/tests/parser_test.py
iotlabwscli-0.1.0.dist-info/DESCRIPTION.rst
iotlabwscli-0.1.0.dist-info/METADATA
iotlabwscli-0.1.0.dist-info/RECORD
iotlabwscli-0.1.0.dist-info/WHEEL
iotlabwscli-0.1.0.dist-info/entry_points.txt
iotlabwscli-0.1.0.dist-info/metadata.json
iotlabwscli-0.1.0.dist-info/top_level.txt
