Metadata-Version: 2.0
Name: iotlabwscli
Version: 0.1.0
Summary: IoT-LAB testbed websocket command-line client
Home-page: http://www.iot-lab.info
Author: IoT-LAB Team
Author-email: admin@iot-lab.info
License: CeCILL v2.1
Download-URL: http://github.com/iot-lab/ws-cli-tools/
Platform: UNKNOWN
Classifier: Development Status :: 4 - Beta
Classifier: Programming Language :: Python
Classifier: Programming Language :: Python :: 2.7
Classifier: Programming Language :: Python :: 3
Classifier: Programming Language :: Python :: 3.4
Classifier: Programming Language :: Python :: 3.5
Classifier: Programming Language :: Python :: 3.6
Classifier: Programming Language :: Python :: 3.7
Classifier: Intended Audience :: End Users/Desktop
Classifier: Environment :: Console
Classifier: Topic :: Utilities
Requires-Dist: argparse
Requires-Dist: iotlabcli (>=2.0)
Requires-Dist: tornado (>=5.1)
